trilium_py/__init__.py
trilium_py/client.py
trilium_py/version.py
trilium_py/web_client.py
trilium_py/utils/__init__.py
trilium_py/utils/file_util.py
trilium_py/utils/html_util.py
trilium_py/utils/image_util.py
trilium_py/utils/markdown_math.py
trilium_py/utils/note_util.py
trilium_py/utils/param_util.py
trilium_py/utils/time_util.py
trilium_py/utils/url_util.py
trilium_py-1.3.3.dist-info/licenses/LICENSE.txt
trilium_py-1.3.3.dist-info/METADATA
trilium_py-1.3.3.dist-info/WHEEL
trilium_py-1.3.3.dist-info/top_level.txt
trilium_py-1.3.3.dist-info/RECORD
