Metadata-Version: 2.4
Name: trilium-py
Version: 1.3.3
Summary: Python client for ETAPI of Trilium Note. With some extra features powered by Python :)
Home-page: https://github.com/nriver/trilium-py
Author: Nriver
Author-email: 
Project-URL: Bug Reports, https://github.com/nriver/trilium-py/issues
Project-URL: Funding, https://github.com/nriver/trilium-py
Project-URL: Say Thanks!, https://github.com/nriver/trilium-py
Project-URL: Source, https://github.com/nriver/trilium-py/
Keywords: trilium,etapi,api client
Classifier: Development Status :: 5 - Production/Stable
Classifier: Intended Audience :: Developers
Classifier: Topic :: Software Development :: Build Tools
Classifier: License :: OSI Approved :: GNU Affero General Public License v3
Classifier: Programming Language :: Python :: 3
Classifier: Programming Language :: Python :: 3.9
Classifier: Programming Language :: Python :: 3.10
Classifier: Programming Language :: Python :: 3.11
Classifier: Programming Language :: Python :: 3.12
Classifier: Programming Language :: Python :: 3.13
Classifier: Programming Language :: Python :: 3 :: Only
Requires-Python: >=3.9, <4
License-File: LICENSE.txt
Requires-Dist: BeautifulSoup4
Requires-Dist: requests
Requires-Dist: markdown2[all]
Requires-Dist: natsort
Requires-Dist: loguru
Requires-Dist: pillow
Requires-Dist: python-dateutil
Requires-Dist: tqdm
Dynamic: author
Dynamic: classifier
Dynamic: description
Dynamic: description-content-type
Dynamic: home-page
Dynamic: keywords
Dynamic: license-file
Dynamic: project-url
Dynamic: requires-dist
Dynamic: requires-python
Dynamic: summary
